efficient_classifier/__init__.py
efficient_classifier/root.py
efficient_classifier/phases/__init__.py
efficient_classifier/phases/phases_implementation/__init__.py
efficient_classifier/phases/phases_implementation/data_preprocessing/__init__.py
efficient_classifier/phases/phases_implementation/data_preprocessing/bounds_config.py
efficient_classifier/phases/phases_implementation/data_preprocessing/class_imbalance.py
efficient_classifier/phases/phases_implementation/data_preprocessing/data_preprocessing.py
efficient_classifier/phases/phases_implementation/data_preprocessing/feature_scaling.py
efficient_classifier/phases/phases_implementation/data_preprocessing/outliers_bounds.py
efficient_classifier/phases/phases_implementation/data_preprocessing/uncomplete_data.py
efficient_classifier/phases/phases_implementation/dataset/__init__.py
efficient_classifier/phases/phases_implementation/dataset/dataset.py
efficient_classifier/phases/phases_implementation/dataset/split/__init__.py
efficient_classifier/phases/phases_implementation/dataset/split/strategies/__init__.py
efficient_classifier/phases/phases_implementation/dataset/split/strategies/base.py
efficient_classifier/phases/phases_implementation/dataset/split/strategies/noTimeSeries.py
efficient_classifier/phases/phases_implementation/dataset/split/strategies/timeSeries.py
efficient_classifier/phases/runners/__init__.py
efficient_classifier/phases/runners/dataPreprocessing_runner.py
efficient_classifier/phases/runners/dataset_runner.py
efficient_classifier/phases/runners/featureAnalysis_runner.py
efficient_classifier/phases/runners/modelling/__init__.py
efficient_classifier/phases/runners/modelling/modelling_runner.py
efficient_classifier/pipeline/__init__.py
efficient_classifier/pipeline/pipeline.py
efficient_classifier/pipeline/pipeline_manager.py
efficient_classifier/pipeline/pipeline_runner.py
efficient_classifier/pipeline/analysis/__init__.py
efficient_classifier/pipeline/analysis/pipelines_analysis.py
efficient_classifier-2.1.2.dist-info/METADATA
efficient_classifier-2.1.2.dist-info/WHEEL
efficient_classifier-2.1.2.dist-info/top_level.txt
efficient_classifier-2.1.2.dist-info/RECORD
